{"nodes": [{"id": "c_my_script_oz_pos_crates_oz_hal_src_types_rs", "label": "types.rs", "file_type": "code", "source_file": "crates/oz-hal/src/types.rs", "source_location": "L1"}, {"id": "c_my_script_oz_pos_crates_oz_hal_src_types_barcode", "label": "Barcode", "file_type": "code", "source_file": "crates/oz-hal/src/types.rs", "source_location": "L7"}, {"id": "string", "label": "String", "file_type": "code", "source_file": "", "source_location": "", "origin_file": "C:\\My Script\\oz-pos\\crates\\oz-hal\\src\\types.rs"}, {"id": "barcodesymbology", "label": "BarcodeSymbology", "file_type": "code", "source_file": "", "source_location": "", "origin_file": "C:\\My Script\\oz-pos\\crates\\oz-hal\\src\\types.rs"}, {"id": "c_my_script_oz_pos_crates_oz_hal_src_types_barcode_new", "label": ".new()", "file_type": "code", "source_file": "crates/oz-hal/src/types.rs", "source_location": "L18"}, {"id": "into", "label": "Into", "file_type": "code", "source_file": "", "source_location": "", "origin_file": "C:\\My Script\\oz-pos\\crates\\oz-hal\\src\\types.rs"}, {"id": "self", "label": "Self", "file_type": "code", "source_file": "", "source_location": "", "origin_file": "C:\\My Script\\oz-pos\\crates\\oz-hal\\src\\types.rs"}, {"id": "c_my_script_oz_pos_crates_oz_hal_src_types_barcodesymbology", "label": "BarcodeSymbology", "file_type": "code", "source_file": "crates/oz-hal/src/types.rs", "source_location": "L30"}, {"id": "c_my_script_oz_pos_crates_oz_hal_src_types_deviceinfo", "label": "DeviceInfo", "file_type": "code", "source_file": "crates/oz-hal/src/types.rs", "source_location": "L47"}, {"id": "c_my_script_oz_pos_crates_oz_hal_src_types_deviceinfo_new", "label": ".new()", "file_type": "code", "source_file": "crates/oz-hal/src/types.rs", "source_location": "L59"}, {"id": "c_my_script_oz_pos_crates_oz_hal_src_types_deviceinfo_display", "label": ".display()", "file_type": "code", "source_file": "crates/oz-hal/src/types.rs", "source_location": "L73"}, {"id": "c_my_script_oz_pos_crates_oz_hal_src_types_barcode_new_defaults_to_any_symbology", "label": "barcode_new_defaults_to_any_symbology()", "file_type": "code", "source_file": "crates/oz-hal/src/types.rs", "source_location": "L83"}, {"id": "c_my_script_oz_pos_crates_oz_hal_src_types_device_info_display_format", "label": "device_info_display_format()", "file_type": "code", "source_file": "crates/oz-hal/src/types.rs", "source_location": "L90"}, {"id": "c_my_script_oz_pos_crates_oz_hal_src_types_barcode_with_explicit_symbology", "label": "barcode_with_explicit_symbology()", "file_type": "code", "source_file": "crates/oz-hal/src/types.rs", "source_location": "L96"}, {"id": "c_my_script_oz_pos_crates_oz_hal_src_types_device_info_empty_serial", "label": "device_info_empty_serial()", "file_type": "code", "source_file": "crates/oz-hal/src/types.rs", "source_location": "L106"}, {"id": "c_my_script_oz_pos_crates_oz_hal_src_types_device_info_long_fields", "label": "device_info_long_fields()", "file_type": "code", "source_file": "crates/oz-hal/src/types.rs", "source_location": "L112"}, {"id": "c_my_script_oz_pos_crates_oz_hal_src_types_barcode_symbology_debug_and_clone", "label": "barcode_symbology_debug_and_clone()", "file_type": "code", "source_file": "crates/oz-hal/src/types.rs", "source_location": "L120"}, {"id": "c_my_script_oz_pos_crates_oz_hal_src_types_barcode_eq_and_hash", "label": "barcode_eq_and_hash()", "file_type": "code", "source_file": "crates/oz-hal/src/types.rs", "source_location": "L136"}, {"id": "c_my_script_oz_pos_crates_oz_hal_src_types_device_info_eq", "label": "device_info_eq()", "file_type": "code", "source_file": "crates/oz-hal/src/types.rs", "source_location": "L152"}, {"id": "c_my_script_oz_pos_crates_oz_hal_src_types_barcode_serde_roundtrip", "label": "barcode_serde_roundtrip()", "file_type": "code", "source_file": "crates/oz-hal/src/types.rs", "source_location": "L161"}, {"id": "c_my_script_oz_pos_crates_oz_hal_src_types_device_info_serde_roundtrip", "label": "device_info_serde_roundtrip()", "file_type": "code", "source_file": "crates/oz-hal/src/types.rs", "source_location": "L172"}], "edges": [{"source": "c_my_script_oz_pos_crates_oz_hal_src_types_rs", "target": "serde", "relation": "imports_from", "confidence": "EXTRACTED", "source_file": "crates/oz-hal/src/types.rs", "source_location": "L3", "weight": 1.0, "context": "import"}, {"source": "c_my_script_oz_pos_crates_oz_hal_src_types_rs", "target": "c_my_script_oz_pos_crates_oz_hal_src_types_barcode", "relation": "contains", "confidence": "EXTRACTED", "source_file": "crates/oz-hal/src/types.rs", "source_location": "L7", "weight": 1.0}, {"source": "c_my_script_oz_pos_crates_oz_hal_src_types_barcode", "target": "string", "relation": "references", "confidence": "EXTRACTED", "source_file": "crates/oz-hal/src/types.rs", "source_location": "L9", "weight": 1.0, "context": "field"}, {"source": "c_my_script_oz_pos_crates_oz_hal_src_types_barcode", "target": "barcodesymbology", "relation": "references", "confidence": "EXTRACTED", "source_file": "crates/oz-hal/src/types.rs", "source_location": "L11", "weight": 1.0, "context": "field"}, {"source": "c_my_script_oz_pos_crates_oz_hal_src_types_barcode", "target": "c_my_script_oz_pos_crates_oz_hal_src_types_barcode_new", "relation": "method", "confidence": "EXTRACTED", "source_file": "crates/oz-hal/src/types.rs", "source_location": "L18", "weight": 1.0}, {"source": "c_my_script_oz_pos_crates_oz_hal_src_types_barcode_new", "target": "into", "relation": "references", "confidence": "EXTRACTED", "source_file": "crates/oz-hal/src/types.rs", "source_location": "L18", "weight": 1.0, "context": "parameter_type"}, {"source": "c_my_script_oz_pos_crates_oz_hal_src_types_barcode_new", "target": "string", "relation": "references", "confidence": "EXTRACTED", "source_file": "crates/oz-hal/src/types.rs", "source_location": "L18", "weight": 1.0, "context": "generic_arg"}, {"source": "c_my_script_oz_pos_crates_oz_hal_src_types_barcode_new", "target": "self", "relation": "references", "confidence": "EXTRACTED", "source_file": "crates/oz-hal/src/types.rs", "source_location": "L18", "weight": 1.0, "context": "return_type"}, {"source": "c_my_script_oz_pos_crates_oz_hal_src_types_rs", "target": "c_my_script_oz_pos_crates_oz_hal_src_types_barcodesymbology", "relation": "contains", "confidence": "EXTRACTED", "source_file": "crates/oz-hal/src/types.rs", "source_location": "L30", "weight": 1.0}, {"source": "c_my_script_oz_pos_crates_oz_hal_src_types_rs", "target": "c_my_script_oz_pos_crates_oz_hal_src_types_deviceinfo", "relation": "contains", "confidence": "EXTRACTED", "source_file": "crates/oz-hal/src/types.rs", "source_location": "L47", "weight": 1.0}, {"source": "c_my_script_oz_pos_crates_oz_hal_src_types_deviceinfo", "target": "string", "relation": "references", "confidence": "EXTRACTED", "source_file": "crates/oz-hal/src/types.rs", "source_location": "L49", "weight": 1.0, "context": "field"}, {"source": "c_my_script_oz_pos_crates_oz_hal_src_types_deviceinfo", "target": "string", "relation": "references", "confidence": "EXTRACTED", "source_file": "crates/oz-hal/src/types.rs", "source_location": "L51", "weight": 1.0, "context": "field"}, {"source": "c_my_script_oz_pos_crates_oz_hal_src_types_deviceinfo", "target": "string", "relation": "references", "confidence": "EXTRACTED", "source_file": "crates/oz-hal/src/types.rs", "source_location": "L53", "weight": 1.0, "context": "field"}, {"source": "c_my_script_oz_pos_crates_oz_hal_src_types_deviceinfo", "target": "c_my_script_oz_pos_crates_oz_hal_src_types_deviceinfo_new", "relation": "method", "confidence": "EXTRACTED", "source_file": "crates/oz-hal/src/types.rs", "source_location": "L59", "weight": 1.0}, {"source": "c_my_script_oz_pos_crates_oz_hal_src_types_deviceinfo_new", "target": "into", "relation": "references", "confidence": "EXTRACTED", "source_file": "crates/oz-hal/src/types.rs", "source_location": "L59", "weight": 1.0, "context": "parameter_type"}, {"source": "c_my_script_oz_pos_crates_oz_hal_src_types_deviceinfo_new", "target": "string", "relation": "references", "confidence": "EXTRACTED", "source_file": "crates/oz-hal/src/types.rs", "source_location": "L59", "weight": 1.0, "context": "generic_arg"}, {"source": "c_my_script_oz_pos_crates_oz_hal_src_types_deviceinfo_new", "target": "into", "relation": "references", "confidence": "EXTRACTED", "source_file": "crates/oz-hal/src/types.rs", "source_location": "L59", "weight": 1.0, "context": "parameter_type"}, {"source": "c_my_script_oz_pos_crates_oz_hal_src_types_deviceinfo_new", "target": "string", "relation": "references", "confidence": "EXTRACTED", "source_file": "crates/oz-hal/src/types.rs", "source_location": "L59", "weight": 1.0, "context": "generic_arg"}, {"source": "c_my_script_oz_pos_crates_oz_hal_src_types_deviceinfo_new", "target": "into", "relation": "references", "confidence": "EXTRACTED", "source_file": "crates/oz-hal/src/types.rs", "source_location": "L59", "weight": 1.0, "context": "parameter_type"}, {"source": "c_my_script_oz_pos_crates_oz_hal_src_types_deviceinfo_new", "target": "string", "relation": "references", "confidence": "EXTRACTED", "source_file": "crates/oz-hal/src/types.rs", "source_location": "L59", "weight": 1.0, "context": "generic_arg"}, {"source": "c_my_script_oz_pos_crates_oz_hal_src_types_deviceinfo_new", "target": "self", "relation": "references", "confidence": "EXTRACTED", "source_file": "crates/oz-hal/src/types.rs", "source_location": "L59", "weight": 1.0, "context": "return_type"}, {"source": "c_my_script_oz_pos_crates_oz_hal_src_types_deviceinfo", "target": "c_my_script_oz_pos_crates_oz_hal_src_types_deviceinfo_display", "relation": "method", "confidence": "EXTRACTED", "source_file": "crates/oz-hal/src/types.rs", "source_location": "L73", "weight": 1.0}, {"source": "c_my_script_oz_pos_crates_oz_hal_src_types_deviceinfo_display", "target": "string", "relation": "references", "confidence": "EXTRACTED", "source_file": "crates/oz-hal/src/types.rs", "source_location": "L73", "weight": 1.0, "context": "return_type"}, {"source": "c_my_script_oz_pos_crates_oz_hal_src_types_rs", "target": "super", "relation": "imports_from", "confidence": "EXTRACTED", "source_file": "crates/oz-hal/src/types.rs", "source_location": "L80", "weight": 1.0, "context": "import"}, {"source": "c_my_script_oz_pos_crates_oz_hal_src_types_rs", "target": "c_my_script_oz_pos_crates_oz_hal_src_types_barcode_new_defaults_to_any_symbology", "relation": "contains", "confidence": "EXTRACTED", "source_file": "crates/oz-hal/src/types.rs", "source_location": "L83", "weight": 1.0}, {"source": "c_my_script_oz_pos_crates_oz_hal_src_types_rs", "target": "c_my_script_oz_pos_crates_oz_hal_src_types_device_info_display_format", "relation": "contains", "confidence": "EXTRACTED", "source_file": "crates/oz-hal/src/types.rs", "source_location": "L90", "weight": 1.0}, {"source": "c_my_script_oz_pos_crates_oz_hal_src_types_rs", "target": "c_my_script_oz_pos_crates_oz_hal_src_types_barcode_with_explicit_symbology", "relation": "contains", "confidence": "EXTRACTED", "source_file": "crates/oz-hal/src/types.rs", "source_location": "L96", "weight": 1.0}, {"source": "c_my_script_oz_pos_crates_oz_hal_src_types_rs", "target": "c_my_script_oz_pos_crates_oz_hal_src_types_device_info_empty_serial", "relation": "contains", "confidence": "EXTRACTED", "source_file": "crates/oz-hal/src/types.rs", "source_location": "L106", "weight": 1.0}, {"source": "c_my_script_oz_pos_crates_oz_hal_src_types_rs", "target": "c_my_script_oz_pos_crates_oz_hal_src_types_device_info_long_fields", "relation": "contains", "confidence": "EXTRACTED", "source_file": "crates/oz-hal/src/types.rs", "source_location": "L112", "weight": 1.0}, {"source": "c_my_script_oz_pos_crates_oz_hal_src_types_rs", "target": "c_my_script_oz_pos_crates_oz_hal_src_types_barcode_symbology_debug_and_clone", "relation": "contains", "confidence": "EXTRACTED", "source_file": "crates/oz-hal/src/types.rs", "source_location": "L120", "weight": 1.0}, {"source": "c_my_script_oz_pos_crates_oz_hal_src_types_rs", "target": "c_my_script_oz_pos_crates_oz_hal_src_types_barcode_eq_and_hash", "relation": "contains", "confidence": "EXTRACTED", "source_file": "crates/oz-hal/src/types.rs", "source_location": "L136", "weight": 1.0}, {"source": "c_my_script_oz_pos_crates_oz_hal_src_types_rs", "target": "c_my_script_oz_pos_crates_oz_hal_src_types_device_info_eq", "relation": "contains", "confidence": "EXTRACTED", "source_file": "crates/oz-hal/src/types.rs", "source_location": "L152", "weight": 1.0}, {"source": "c_my_script_oz_pos_crates_oz_hal_src_types_rs", "target": "c_my_script_oz_pos_crates_oz_hal_src_types_barcode_serde_roundtrip", "relation": "contains", "confidence": "EXTRACTED", "source_file": "crates/oz-hal/src/types.rs", "source_location": "L161", "weight": 1.0}, {"source": "c_my_script_oz_pos_crates_oz_hal_src_types_rs", "target": "c_my_script_oz_pos_crates_oz_hal_src_types_device_info_serde_roundtrip", "relation": "contains", "confidence": "EXTRACTED", "source_file": "crates/oz-hal/src/types.rs", "source_location": "L172", "weight": 1.0}, {"source": "c_my_script_oz_pos_crates_oz_hal_src_types_barcode_new_defaults_to_any_symbology", "target": "c_my_script_oz_pos_crates_oz_hal_src_types_deviceinfo_new", "relation": "calls", "context": "call", "confidence": "EXTRACTED", "source_file": "crates/oz-hal/src/types.rs", "source_location": "L84", "weight": 1.0}, {"source": "c_my_script_oz_pos_crates_oz_hal_src_types_device_info_display_format", "target": "c_my_script_oz_pos_crates_oz_hal_src_types_deviceinfo_new", "relation": "calls", "context": "call", "confidence": "EXTRACTED", "source_file": "crates/oz-hal/src/types.rs", "source_location": "L91", "weight": 1.0}, {"source": "c_my_script_oz_pos_crates_oz_hal_src_types_device_info_empty_serial", "target": "c_my_script_oz_pos_crates_oz_hal_src_types_deviceinfo_new", "relation": "calls", "context": "call", "confidence": "EXTRACTED", "source_file": "crates/oz-hal/src/types.rs", "source_location": "L107", "weight": 1.0}, {"source": "c_my_script_oz_pos_crates_oz_hal_src_types_device_info_long_fields", "target": "c_my_script_oz_pos_crates_oz_hal_src_types_deviceinfo_new", "relation": "calls", "context": "call", "confidence": "EXTRACTED", "source_file": "crates/oz-hal/src/types.rs", "source_location": "L113", "weight": 1.0}, {"source": "c_my_script_oz_pos_crates_oz_hal_src_types_barcode_eq_and_hash", "target": "c_my_script_oz_pos_crates_oz_hal_src_types_deviceinfo_new", "relation": "calls", "context": "call", "confidence": "EXTRACTED", "source_file": "crates/oz-hal/src/types.rs", "source_location": "L138", "weight": 1.0}, {"source": "c_my_script_oz_pos_crates_oz_hal_src_types_device_info_eq", "target": "c_my_script_oz_pos_crates_oz_hal_src_types_deviceinfo_new", "relation": "calls", "context": "call", "confidence": "EXTRACTED", "source_file": "crates/oz-hal/src/types.rs", "source_location": "L153", "weight": 1.0}, {"source": "c_my_script_oz_pos_crates_oz_hal_src_types_device_info_serde_roundtrip", "target": "c_my_script_oz_pos_crates_oz_hal_src_types_deviceinfo_new", "relation": "calls", "context": "call", "confidence": "EXTRACTED", "source_file": "crates/oz-hal/src/types.rs", "source_location": "L173", "weight": 1.0}], "raw_calls": []}