{"nodes": [{"id": "c_my_script_oz_pos_modules_currency_src_lib_rs", "label": "lib.rs", "file_type": "code", "source_file": "modules/currency/src/lib.rs", "source_location": "L1"}, {"id": "c_my_script_oz_pos_modules_currency_src_lib_currencymodule", "label": "CurrencyModule", "file_type": "code", "source_file": "modules/currency/src/lib.rs", "source_location": "L49"}, {"id": "c_my_script_oz_pos_modules_currency_src_lib_currencymodule_new", "label": ".new()", "file_type": "code", "source_file": "modules/currency/src/lib.rs", "source_location": "L53"}, {"id": "self", "label": "Self", "file_type": "code", "source_file": "", "source_location": "", "origin_file": "C:\\My Script\\oz-pos\\modules\\currency\\src\\lib.rs"}, {"id": "default", "label": "Default", "file_type": "code", "source_file": "", "source_location": "", "origin_file": "C:\\My Script\\oz-pos\\modules\\currency\\src\\lib.rs"}, {"id": "c_my_script_oz_pos_modules_currency_src_lib_currencymodule_default", "label": ".default()", "file_type": "code", "source_file": "modules/currency/src/lib.rs", "source_location": "L59"}, {"id": "module", "label": "Module", "file_type": "code", "source_file": "", "source_location": "", "origin_file": "C:\\My Script\\oz-pos\\modules\\currency\\src\\lib.rs"}, {"id": "c_my_script_oz_pos_modules_currency_src_lib_currencymodule_id", "label": ".id()", "file_type": "code", "source_file": "modules/currency/src/lib.rs", "source_location": "L65"}, {"id": "c_my_script_oz_pos_modules_currency_src_lib_currencymodule_on_load", "label": ".on_load()", "file_type": "code", "source_file": "modules/currency/src/lib.rs", "source_location": "L69"}, {"id": "moduleresult", "label": "ModuleResult", "file_type": "code", "source_file": "", "source_location": "", "origin_file": "C:\\My Script\\oz-pos\\modules\\currency\\src\\lib.rs"}, {"id": "c_my_script_oz_pos_modules_currency_src_lib_currencymodule_on_start", "label": ".on_start()", "file_type": "code", "source_file": "modules/currency/src/lib.rs", "source_location": "L77"}, {"id": "c_my_script_oz_pos_modules_currency_src_lib_currencymodule_on_stop", "label": ".on_stop()", "file_type": "code", "source_file": "modules/currency/src/lib.rs", "source_location": "L85"}, {"id": "c_my_script_oz_pos_modules_currency_src_lib_currency_module_id", "label": "currency_module_id()", "file_type": "code", "source_file": "modules/currency/src/lib.rs", "source_location": "L102"}, {"id": "c_my_script_oz_pos_modules_currency_src_lib_currency_module_lifecycle", "label": "currency_module_lifecycle()", "file_type": "code", "source_file": "modules/currency/src/lib.rs", "source_location": "L108"}, {"id": "c_my_script_oz_pos_modules_currency_src_lib_currency_module_duplicate_registration_fails", "label": "currency_module_duplicate_registration_fails()", "file_type": "code", "source_file": "modules/currency/src/lib.rs", "source_location": "L126"}, {"id": "c_my_script_oz_pos_modules_currency_src_lib_currency_module_on_load_succeeds", "label": "currency_module_on_load_succeeds()", "file_type": "code", "source_file": "modules/currency/src/lib.rs", "source_location": "L134"}, {"id": "c_my_script_oz_pos_modules_currency_src_lib_currency_module_on_start_succeeds", "label": "currency_module_on_start_succeeds()", "file_type": "code", "source_file": "modules/currency/src/lib.rs", "source_location": "L140"}, {"id": "c_my_script_oz_pos_modules_currency_src_lib_currency_module_on_stop_succeeds", "label": "currency_module_on_stop_succeeds()", "file_type": "code", "source_file": "modules/currency/src/lib.rs", "source_location": "L146"}, {"id": "c_my_script_oz_pos_modules_currency_src_lib_currency_module_full_lifecycle_with_kernel", "label": "currency_module_full_lifecycle_with_kernel()", "file_type": "code", "source_file": "modules/currency/src/lib.rs", "source_location": "L152"}, {"id": "c_my_script_oz_pos_modules_currency_src_lib_multiple_modules_can_coexist", "label": "multiple_modules_can_coexist()", "file_type": "code", "source_file": "modules/currency/src/lib.rs", "source_location": "L166"}, {"id": "c_my_script_oz_pos_modules_currency_src_lib_othermodule", "label": "OtherModule", "file_type": "code", "source_file": "modules/currency/src/lib.rs", "source_location": "L179"}, {"id": "c_my_script_oz_pos_modules_currency_src_lib_othermodule_id", "label": ".id()", "file_type": "code", "source_file": "modules/currency/src/lib.rs", "source_location": "L182"}, {"id": "c_my_script_oz_pos_modules_currency_src_lib_othermodule_on_load", "label": ".on_load()", "file_type": "code", "source_file": "modules/currency/src/lib.rs", "source_location": "L186"}, {"id": "c_my_script_oz_pos_modules_currency_src_lib_othermodule_on_start", "label": ".on_start()", "file_type": "code", "source_file": "modules/currency/src/lib.rs", "source_location": "L189"}, {"id": "c_my_script_oz_pos_modules_currency_src_lib_othermodule_on_stop", "label": ".on_stop()", "file_type": "code", "source_file": "modules/currency/src/lib.rs", "source_location": "L192"}], "edges": [{"source": "c_my_script_oz_pos_modules_currency_src_lib_rs", "target": "currency", "relation": "imports_from", "confidence": "EXTRACTED", "source_file": "modules/currency/src/lib.rs", "source_location": "L35", "weight": 1.0, "context": "import"}, {"source": "c_my_script_oz_pos_modules_currency_src_lib_rs", "target": "exchangeraterow", "relation": "imports_from", "confidence": "EXTRACTED", "source_file": "modules/currency/src/lib.rs", "source_location": "L36", "weight": 1.0, "context": "import"}, {"source": "c_my_script_oz_pos_modules_currency_src_lib_rs", "target": "debug", "relation": "imports_from", "confidence": "EXTRACTED", "source_file": "modules/currency/src/lib.rs", "source_location": "L38", "weight": 1.0, "context": "import"}, {"source": "c_my_script_oz_pos_modules_currency_src_lib_rs", "target": "contracts", "relation": "imports_from", "confidence": "EXTRACTED", "source_file": "modules/currency/src/lib.rs", "source_location": "L40", "weight": 1.0, "context": "import"}, {"source": "c_my_script_oz_pos_modules_currency_src_lib_rs", "target": "info", "relation": "imports_from", "confidence": "EXTRACTED", "source_file": "modules/currency/src/lib.rs", "source_location": "L41", "weight": 1.0, "context": "import"}, {"source": "c_my_script_oz_pos_modules_currency_src_lib_rs", "target": "c_my_script_oz_pos_modules_currency_src_lib_currencymodule", "relation": "contains", "confidence": "EXTRACTED", "source_file": "modules/currency/src/lib.rs", "source_location": "L49", "weight": 1.0}, {"source": "c_my_script_oz_pos_modules_currency_src_lib_currencymodule", "target": "c_my_script_oz_pos_modules_currency_src_lib_currencymodule_new", "relation": "method", "confidence": "EXTRACTED", "source_file": "modules/currency/src/lib.rs", "source_location": "L53", "weight": 1.0}, {"source": "c_my_script_oz_pos_modules_currency_src_lib_currencymodule_new", "target": "self", "relation": "references", "confidence": "EXTRACTED", "source_file": "modules/currency/src/lib.rs", "source_location": "L53", "weight": 1.0, "context": "return_type"}, {"source": "c_my_script_oz_pos_modules_currency_src_lib_currencymodule", "target": "default", "relation": "implements", "confidence": "EXTRACTED", "source_file": "modules/currency/src/lib.rs", "source_location": "L58", "weight": 1.0}, {"source": "c_my_script_oz_pos_modules_currency_src_lib_currencymodule", "target": "c_my_script_oz_pos_modules_currency_src_lib_currencymodule_default", "relation": "method", "confidence": "EXTRACTED", "source_file": "modules/currency/src/lib.rs", "source_location": "L59", "weight": 1.0}, {"source": "c_my_script_oz_pos_modules_currency_src_lib_currencymodule_default", "target": "self", "relation": "references", "confidence": "EXTRACTED", "source_file": "modules/currency/src/lib.rs", "source_location": "L59", "weight": 1.0, "context": "return_type"}, {"source": "c_my_script_oz_pos_modules_currency_src_lib_currencymodule", "target": "module", "relation": "implements", "confidence": "EXTRACTED", "source_file": "modules/currency/src/lib.rs", "source_location": "L64", "weight": 1.0}, {"source": "c_my_script_oz_pos_modules_currency_src_lib_currencymodule", "target": "c_my_script_oz_pos_modules_currency_src_lib_currencymodule_id", "relation": "method", "confidence": "EXTRACTED", "source_file": "modules/currency/src/lib.rs", "source_location": "L65", "weight": 1.0}, {"source": "c_my_script_oz_pos_modules_currency_src_lib_currencymodule", "target": "c_my_script_oz_pos_modules_currency_src_lib_currencymodule_on_load", "relation": "method", "confidence": "EXTRACTED", "source_file": "modules/currency/src/lib.rs", "source_location": "L69", "weight": 1.0}, {"source": "c_my_script_oz_pos_modules_currency_src_lib_currencymodule_on_load", "target": "moduleresult", "relation": "references", "confidence": "EXTRACTED", "source_file": "modules/currency/src/lib.rs", "source_location": "L69", "weight": 1.0, "context": "return_type"}, {"source": "c_my_script_oz_pos_modules_currency_src_lib_currencymodule", "target": "c_my_script_oz_pos_modules_currency_src_lib_currencymodule_on_start", "relation": "method", "confidence": "EXTRACTED", "source_file": "modules/currency/src/lib.rs", "source_location": "L77", "weight": 1.0}, {"source": "c_my_script_oz_pos_modules_currency_src_lib_currencymodule_on_start", "target": "moduleresult", "relation": "references", "confidence": "EXTRACTED", "source_file": "modules/currency/src/lib.rs", "source_location": "L77", "weight": 1.0, "context": "return_type"}, {"source": "c_my_script_oz_pos_modules_currency_src_lib_currencymodule", "target": "c_my_script_oz_pos_modules_currency_src_lib_currencymodule_on_stop", "relation": "method", "confidence": "EXTRACTED", "source_file": "modules/currency/src/lib.rs", "source_location": "L85", "weight": 1.0}, {"source": "c_my_script_oz_pos_modules_currency_src_lib_currencymodule_on_stop", "target": "moduleresult", "relation": "references", "confidence": "EXTRACTED", "source_file": "modules/currency/src/lib.rs", "source_location": "L85", "weight": 1.0, "context": "return_type"}, {"source": "c_my_script_oz_pos_modules_currency_src_lib_rs", "target": "super", "relation": "imports_from", "confidence": "EXTRACTED", "source_file": "modules/currency/src/lib.rs", "source_location": "L98", "weight": 1.0, "context": "import"}, {"source": "c_my_script_oz_pos_modules_currency_src_lib_rs", "target": "kernel", "relation": "imports_from", "confidence": "EXTRACTED", "source_file": "modules/currency/src/lib.rs", "source_location": "L99", "weight": 1.0, "context": "import"}, {"source": "c_my_script_oz_pos_modules_currency_src_lib_rs", "target": "c_my_script_oz_pos_modules_currency_src_lib_currency_module_id", "relation": "contains", "confidence": "EXTRACTED", "source_file": "modules/currency/src/lib.rs", "source_location": "L102", "weight": 1.0}, {"source": "c_my_script_oz_pos_modules_currency_src_lib_rs", "target": "c_my_script_oz_pos_modules_currency_src_lib_currency_module_lifecycle", "relation": "contains", "confidence": "EXTRACTED", "source_file": "modules/currency/src/lib.rs", "source_location": "L108", "weight": 1.0}, {"source": "c_my_script_oz_pos_modules_currency_src_lib_rs", "target": "c_my_script_oz_pos_modules_currency_src_lib_currency_module_duplicate_registration_fails", "relation": "contains", "confidence": "EXTRACTED", "source_file": "modules/currency/src/lib.rs", "source_location": "L126", "weight": 1.0}, {"source": "c_my_script_oz_pos_modules_currency_src_lib_rs", "target": "c_my_script_oz_pos_modules_currency_src_lib_currency_module_on_load_succeeds", "relation": "contains", "confidence": "EXTRACTED", "source_file": "modules/currency/src/lib.rs", "source_location": "L134", "weight": 1.0}, {"source": "c_my_script_oz_pos_modules_currency_src_lib_rs", "target": "c_my_script_oz_pos_modules_currency_src_lib_currency_module_on_start_succeeds", "relation": "contains", "confidence": "EXTRACTED", "source_file": "modules/currency/src/lib.rs", "source_location": "L140", "weight": 1.0}, {"source": "c_my_script_oz_pos_modules_currency_src_lib_rs", "target": "c_my_script_oz_pos_modules_currency_src_lib_currency_module_on_stop_succeeds", "relation": "contains", "confidence": "EXTRACTED", "source_file": "modules/currency/src/lib.rs", "source_location": "L146", "weight": 1.0}, {"source": "c_my_script_oz_pos_modules_currency_src_lib_rs", "target": "c_my_script_oz_pos_modules_currency_src_lib_currency_module_full_lifecycle_with_kernel", "relation": "contains", "confidence": "EXTRACTED", "source_file": "modules/currency/src/lib.rs", "source_location": "L152", "weight": 1.0}, {"source": "c_my_script_oz_pos_modules_currency_src_lib_rs", "target": "c_my_script_oz_pos_modules_currency_src_lib_multiple_modules_can_coexist", "relation": "contains", "confidence": "EXTRACTED", "source_file": "modules/currency/src/lib.rs", "source_location": "L166", "weight": 1.0}, {"source": "c_my_script_oz_pos_modules_currency_src_lib_rs", "target": "c_my_script_oz_pos_modules_currency_src_lib_othermodule", "relation": "contains", "confidence": "EXTRACTED", "source_file": "modules/currency/src/lib.rs", "source_location": "L179", "weight": 1.0}, {"source": "c_my_script_oz_pos_modules_currency_src_lib_othermodule", "target": "module", "relation": "implements", "confidence": "EXTRACTED", "source_file": "modules/currency/src/lib.rs", "source_location": "L181", "weight": 1.0}, {"source": "c_my_script_oz_pos_modules_currency_src_lib_othermodule", "target": "c_my_script_oz_pos_modules_currency_src_lib_othermodule_id", "relation": "method", "confidence": "EXTRACTED", "source_file": "modules/currency/src/lib.rs", "source_location": "L182", "weight": 1.0}, {"source": "c_my_script_oz_pos_modules_currency_src_lib_othermodule", "target": "c_my_script_oz_pos_modules_currency_src_lib_othermodule_on_load", "relation": "method", "confidence": "EXTRACTED", "source_file": "modules/currency/src/lib.rs", "source_location": "L186", "weight": 1.0}, {"source": "c_my_script_oz_pos_modules_currency_src_lib_othermodule_on_load", "target": "moduleresult", "relation": "references", "confidence": "EXTRACTED", "source_file": "modules/currency/src/lib.rs", "source_location": "L186", "weight": 1.0, "context": "return_type"}, {"source": "c_my_script_oz_pos_modules_currency_src_lib_othermodule", "target": "c_my_script_oz_pos_modules_currency_src_lib_othermodule_on_start", "relation": "method", "confidence": "EXTRACTED", "source_file": "modules/currency/src/lib.rs", "source_location": "L189", "weight": 1.0}, {"source": "c_my_script_oz_pos_modules_currency_src_lib_othermodule_on_start", "target": "moduleresult", "relation": "references", "confidence": "EXTRACTED", "source_file": "modules/currency/src/lib.rs", "source_location": "L189", "weight": 1.0, "context": "return_type"}, {"source": "c_my_script_oz_pos_modules_currency_src_lib_othermodule", "target": "c_my_script_oz_pos_modules_currency_src_lib_othermodule_on_stop", "relation": "method", "confidence": "EXTRACTED", "source_file": "modules/currency/src/lib.rs", "source_location": "L192", "weight": 1.0}, {"source": "c_my_script_oz_pos_modules_currency_src_lib_othermodule_on_stop", "target": "moduleresult", "relation": "references", "confidence": "EXTRACTED", "source_file": "modules/currency/src/lib.rs", "source_location": "L192", "weight": 1.0, "context": "return_type"}, {"source": "c_my_script_oz_pos_modules_currency_src_lib_currencymodule_default", "target": "c_my_script_oz_pos_modules_currency_src_lib_currencymodule_new", "relation": "calls", "context": "call", "confidence": "EXTRACTED", "source_file": "modules/currency/src/lib.rs", "source_location": "L60", "weight": 1.0}, {"source": "c_my_script_oz_pos_modules_currency_src_lib_currency_module_id", "target": "c_my_script_oz_pos_modules_currency_src_lib_currencymodule_new", "relation": "calls", "context": "call", "confidence": "EXTRACTED", "source_file": "modules/currency/src/lib.rs", "source_location": "L103", "weight": 1.0}, {"source": "c_my_script_oz_pos_modules_currency_src_lib_currency_module_lifecycle", "target": "c_my_script_oz_pos_modules_currency_src_lib_currencymodule_new", "relation": "calls", "context": "call", "confidence": "EXTRACTED", "source_file": "modules/currency/src/lib.rs", "source_location": "L109", "weight": 1.0}, {"source": "c_my_script_oz_pos_modules_currency_src_lib_currency_module_duplicate_registration_fails", "target": "c_my_script_oz_pos_modules_currency_src_lib_currencymodule_new", "relation": "calls", "context": "call", "confidence": "EXTRACTED", "source_file": "modules/currency/src/lib.rs", "source_location": "L127", "weight": 1.0}, {"source": "c_my_script_oz_pos_modules_currency_src_lib_currency_module_on_load_succeeds", "target": "c_my_script_oz_pos_modules_currency_src_lib_currencymodule_new", "relation": "calls", "context": "call", "confidence": "EXTRACTED", "source_file": "modules/currency/src/lib.rs", "source_location": "L135", "weight": 1.0}, {"source": "c_my_script_oz_pos_modules_currency_src_lib_currency_module_on_start_succeeds", "target": "c_my_script_oz_pos_modules_currency_src_lib_currencymodule_new", "relation": "calls", "context": "call", "confidence": "EXTRACTED", "source_file": "modules/currency/src/lib.rs", "source_location": "L141", "weight": 1.0}, {"source": "c_my_script_oz_pos_modules_currency_src_lib_currency_module_on_stop_succeeds", "target": "c_my_script_oz_pos_modules_currency_src_lib_currencymodule_new", "relation": "calls", "context": "call", "confidence": "EXTRACTED", "source_file": "modules/currency/src/lib.rs", "source_location": "L147", "weight": 1.0}, {"source": "c_my_script_oz_pos_modules_currency_src_lib_currency_module_full_lifecycle_with_kernel", "target": "c_my_script_oz_pos_modules_currency_src_lib_currencymodule_new", "relation": "calls", "context": "call", "confidence": "EXTRACTED", "source_file": "modules/currency/src/lib.rs", "source_location": "L153", "weight": 1.0}, {"source": "c_my_script_oz_pos_modules_currency_src_lib_multiple_modules_can_coexist", "target": "c_my_script_oz_pos_modules_currency_src_lib_currencymodule_new", "relation": "calls", "context": "call", "confidence": "EXTRACTED", "source_file": "modules/currency/src/lib.rs", "source_location": "L167", "weight": 1.0}], "raw_calls": [{"caller_nid": "c_my_script_oz_pos_modules_currency_src_lib_currency_module_lifecycle", "callee": "register", "is_member_call": true, "source_file": "modules/currency/src/lib.rs", "source_location": "L110"}, {"caller_nid": "c_my_script_oz_pos_modules_currency_src_lib_currency_module_lifecycle", "callee": "load_all", "is_member_call": true, "source_file": "modules/currency/src/lib.rs", "source_location": "L114"}, {"caller_nid": "c_my_script_oz_pos_modules_currency_src_lib_currency_module_lifecycle", "callee": "start_all", "is_member_call": true, "source_file": "modules/currency/src/lib.rs", "source_location": "L117"}, {"caller_nid": "c_my_script_oz_pos_modules_currency_src_lib_currency_module_lifecycle", "callee": "stop_all", "is_member_call": true, "source_file": "modules/currency/src/lib.rs", "source_location": "L120"}, {"caller_nid": "c_my_script_oz_pos_modules_currency_src_lib_currency_module_duplicate_registration_fails", "callee": "register", "is_member_call": true, "source_file": "modules/currency/src/lib.rs", "source_location": "L128"}, {"caller_nid": "c_my_script_oz_pos_modules_currency_src_lib_currency_module_duplicate_registration_fails", "callee": "register", "is_member_call": true, "source_file": "modules/currency/src/lib.rs", "source_location": "L129"}, {"caller_nid": "c_my_script_oz_pos_modules_currency_src_lib_currency_module_full_lifecycle_with_kernel", "callee": "register", "is_member_call": true, "source_file": "modules/currency/src/lib.rs", "source_location": "L154"}, {"caller_nid": "c_my_script_oz_pos_modules_currency_src_lib_currency_module_full_lifecycle_with_kernel", "callee": "load_all", "is_member_call": true, "source_file": "modules/currency/src/lib.rs", "source_location": "L157"}, {"caller_nid": "c_my_script_oz_pos_modules_currency_src_lib_currency_module_full_lifecycle_with_kernel", "callee": "start_all", "is_member_call": true, "source_file": "modules/currency/src/lib.rs", "source_location": "L158"}, {"caller_nid": "c_my_script_oz_pos_modules_currency_src_lib_currency_module_full_lifecycle_with_kernel", "callee": "stop_all", "is_member_call": true, "source_file": "modules/currency/src/lib.rs", "source_location": "L159"}, {"caller_nid": "c_my_script_oz_pos_modules_currency_src_lib_multiple_modules_can_coexist", "callee": "register", "is_member_call": true, "source_file": "modules/currency/src/lib.rs", "source_location": "L168"}, {"caller_nid": "c_my_script_oz_pos_modules_currency_src_lib_multiple_modules_can_coexist", "callee": "register", "is_member_call": true, "source_file": "modules/currency/src/lib.rs", "source_location": "L169"}]}